[
  {
    "id": "1",
    "syncToken": "0",
    "metaData": {
      "createdByRef": null,
      "createTime": "2026-01-08T04:33:04.000+00:00",
      "lastModifiedByRef": null,
      "lastUpdatedTime": "2026-01-08T04:33:04.000+00:00",
      "lastChangedInQB": null,
      "synchronized": null
    },
    "customField": [],
    "attachableRef": [],
    "domain": "QBO",
    "status": null,
    "sparse": false,
    "name": "Services",
    "subAccount": false,
    "parentRef": null,
    "description": null,
    "fullyQualifiedName": "Services",
    "accountAlias": null,
    "txnLocationType": null,
    "active": true,
    "classification": "ASSET",
    "accountType": "OTHER_CURRENT_ASSET",
    "accountSubType": null,
    "accountPurposes": [],
    "acctNum": null,
    "acctNumExtn": null,
    "bankNum": null,
    "openingBalance": null,
    "openingBalanceDate": null,
    "currentBalance": 503.55,
    "currentBalanceWithSubAccounts": 503.55,
    "currencyRef": {
      "value": "USD",
      "name": "United States Dollar",
      "type": null
    },
    "taxAccount": null,
    "taxCodeRef": null,
    "onlineBankingEnabled": null,
    "journalCodeRef": null,
    "accountEx": null,
    "finame": null
  },
  {
    "id": "4",
    "syncToken": "0",
    "metaData": {
      "createdByRef": null,
      "createTime": "2026-01-08T04:33:04.000+00:00",
      "lastModifiedByRef": null,
      "lastUpdatedTime": "2026-01-08T04:33:04.000+00:00",
      "lastChangedInQB": null,
      "synchronized": null
    },
    "customField": [],
    "attachableRef": [],
    "domain": "QBO",
    "status": null,
    "sparse": false,
    "name": "Undeposited Funds",
    "subAccount": false,
    "parentRef": null,
    "description": null,
    "fullyQualifiedName": "Undeposited Funds",
    "accountAlias": null,
    "txnLocationType": null,
    "active": true,
    "classification": "ASSET",
    "accountType": "OTHER_CURRENT_ASSET",
    "accountSubType": null,
    "accountPurposes": [],
    "acctNum": null,
    "acctNumExtn": null,
    "bankNum": null,
    "openingBalance": null,
    "openingBalanceDate": null,
    "currentBalance": 2062.52,
    "currentBalanceWithSubAccounts": 2062.52,
    "currencyRef": {
      "value": "USD",
      "name": "United States Dollar",
      "type": null
    },
    "taxAccount": null,
    "taxCodeRef": null,
    "onlineBankingEnabled": null,
    "journalCodeRef": null,
    "accountEx": null,
    "finame": null
  },
  {
    "id": "7",
    "syncToken": "0",
    "metaData": {
      "createdByRef": null,
      "createTime": "2026-01-08T04:33:04.000+00:00",
      "lastModifiedByRef": null,
      "lastUpdatedTime": "2026-01-08T04:33:04.000+00:00",
      "lastChangedInQB": null,
      "synchronized": null
    },
    "customField": [],
    "attachableRef": [],
    "domain": "QBO",
    "status": null,
    "sparse": false,
    "name": "Advertising",
    "subAccount": false,
    "parentRef": null,
    "description": null,
    "fullyQualifiedName": "Advertising",
    "accountAlias": null,
    "txnLocationType": null,
    "active": true,
    "classification": "EXPENSE",
    "accountType": "EXPENSE",
    "accountSubType": null,
    "accountPurposes": [],
    "acctNum": null,
    "acctNumExtn": null,
    "bankNum": null,
    "openingBalance": null,
    "openingBalanceDate": null,
    "currentBalance": 74.86,
    "currentBalanceWithSubAccounts": 74.86,
    "currencyRef": {
      "value": "USD",
      "name": "United States Dollar",
      "type": null
    },
    "taxAccount": null,
    "taxCodeRef": null,
    "onlineBankingEnabled": null,
    "journalCodeRef": null,
    "accountEx": null,
    "finame": null
  },
  {
    "id": "11",
    "syncToken": "0",
    "metaData": {
      "createdByRef": null,
      "createTime": "2026-01-08T04:33:04.000+00:00",
      "lastModifiedByRef": null,
      "lastUpdatedTime": "2026-01-08T04:33:04.000+00:00",
      "lastChangedInQB": null,
      "synchronized": null
    },
    "customField": [],
    "attachableRef": [],
    "domain": "QBO",
    "status": null,
    "sparse": false,
    "name": "Insurance",
    "subAccount": false,
    "parentRef": null,
    "description": null,
    "fullyQualifiedName": "Insurance",
    "accountAlias": null,
    "txnLocationType": null,
    "active": true,
    "classification": "EXPENSE",
    "accountType": "EXPENSE",
    "accountSubType": null,
    "accountPurposes": [],
    "acctNum": null,
    "acctNumExtn": null,
    "bankNum": null,
    "openingBalance": null,
    "openingBalanceDate": null,
    "currentBalance": 241.23,
    "currentBalanceWithSubAccounts": 241.23,
    "currencyRef": {
      "value": "USD",
      "name": "United States Dollar",
      "type": null
    },
    "taxAccount": null,
    "taxCodeRef": null,
    "onlineBankingEnabled": null,
    "journalCodeRef": null,
    "accountEx": null,
    "finame": null
  },
  {
    "id": "12",
    "syncToken": "0",
    "metaData": {
      "createdByRef": null,
      "createTime": "2026-01-08T04:33:04.000+00:00",
      "lastModifiedByRef": null,
      "lastUpdatedTime": "2026-01-08T04:33:04.000+00:00",
      "lastChangedInQB": null,
      "synchronized": null
    },
    "customField": [],
    "attachableRef": [],
    "domain": "QBO",
    "status": null,
    "sparse": false,
    "name": "Legal & Professional Fees",
    "subAccount": false,
    "parentRef": null,
    "description": null,
    "fullyQualifiedName": "Legal & Professional Fees",
    "accountAlias": null,
    "txnLocationType": null,
    "active": true,
    "classification": "EXPENSE",
    "accountType": "EXPENSE",
    "accountSubType": null,
    "accountPurposes": [],
    "acctNum": null,
    "acctNumExtn": null,
    "bankNum": null,
    "openingBalance": null,
    "openingBalanceDate": null,
    "currentBalance": 0.0,
    "currentBalanceWithSubAccounts": 0.0,
    "currencyRef": {
      "value": "USD",
      "name": "United States Dollar",
      "type": null
    },
    "taxAccount": null,
    "taxCodeRef": null,
    "onlineBankingEnabled": null,
    "journalCodeRef": null,
    "accountEx": null,
    "finame": null
  },
  {
    "id": "13",
    "syncToken": "0",
    "metaData": {
      "createdByRef": null,
      "createTime": "2026-01-08T04:33:04.000+00:00",
      "lastModifiedByRef": null,
      "lastUpdatedTime": "2026-01-08T04:33:04.000+00:00",
      "lastChangedInQB": null,
      "synchronized": null
    },
    "customField": [],
    "attachableRef": [],
    "domain": "QBO",
    "status": null,
    "sparse": false,
    "name": "Meals and Entertainment",
    "subAccount": false,
    "parentRef": null,
    "description": null,
    "fullyQualifiedName": "Meals and Entertainment",
    "accountAlias": null,
    "txnLocationType": null,
    "active": true,
    "classification": "ASSET",
    "accountType": "OTHER_CURRENT_ASSET",
    "accountSubType": null,
    "accountPurposes": [],
    "acctNum": null,
    "acctNumExtn": null,
    "bankNum": null,
    "openingBalance": null,
    "openingBalanceDate": null,
    "currentBalance": 28.49,
    "currentBalanceWithSubAccounts": 28.49,
    "currencyRef": {
      "value": "USD",
      "name": "United States Dollar",
      "type": null
    },
    "taxAccount": null,
    "taxCodeRef": null,
    "onlineBankingEnabled": null,
    "journalCodeRef": null,
    "accountEx": null,
    "finame": null
  },
  {
    "id": "14",
    "syncToken": "0",
    "metaData": {
      "createdByRef": null,
      "createTime": "2026-01-08T04:33:04.000+00:00",
      "lastModifiedByRef": null,
      "lastUpdatedTime": "2026-01-08T04:33:04.000+00:00",
      "lastChangedInQB": null,
      "synchronized": null
    },
    "customField": [],
    "attachableRef": [],
    "domain": "QBO",
    "status": null,
    "sparse": false,
    "name": "Miscellaneous",
    "subAccount": false,
    "parentRef": null,
    "description": null,
    "fullyQualifiedName": "Miscellaneous",
    "accountAlias": null,
    "txnLocationType": null,
    "active": true,
    "classification": "ASSET",
    "accountType": "OTHER_CURRENT_ASSET",
    "accountSubType": null,
    "accountPurposes": [],
    "acctNum": null,
    "acctNumExtn": null,
    "bankNum": null,
    "openingBalance": null,
    "openingBalanceDate": null,
    "currentBalance": 2916.0,
    "currentBalanceWithSubAccounts": 2916.0,
    "currencyRef": {
      "value": "USD",
      "name": "United States Dollar",
      "type": null
    },
    "taxAccount": null,
    "taxCodeRef": null,
    "onlineBankingEnabled": null,
    "journalCodeRef": null,
    "accountEx": null,
    "finame": null
  },
  {
    "id": "15",
    "syncToken": "0",
    "metaData": {
      "createdByRef": null,
      "createTime": "2026-01-08T04:33:04.000+00:00",
      "lastModifiedByRef": null,
      "lastUpdatedTime": "2026-01-08T04:33:04.000+00:00",
      "lastChangedInQB": null,
      "synchronized": null
    },
    "customField": [],
    "attachableRef": [],
    "domain": "QBO",
    "status": null,
    "sparse": false,
    "name": "Office Expenses",
    "subAccount": false,
    "parentRef": null,
    "description": null,
    "fullyQualifiedName": "Office Expenses",
    "accountAlias": null,
    "txnLocationType": null,
    "active": true,
    "classification": "ASSET",
    "accountType": "OTHER_CURRENT_ASSET",
    "accountSubType": null,
    "accountPurposes": [],
    "acctNum": null,
    "acctNumExtn": null,
    "bankNum": null,
    "openingBalance": null,
    "openingBalanceDate": null,
    "currentBalance": 18.08,
    "currentBalanceWithSubAccounts": 18.08,
    "currencyRef": {
      "value": "USD",
      "name": "United States Dollar",
      "type": null
    },
    "taxAccount": null,
    "taxCodeRef": null,
    "onlineBankingEnabled": null,
    "journalCodeRef": null,
    "accountEx": null,
    "finame": null
  },
  {
    "id": "17",
    "syncToken": "0",
    "metaData": {
      "createdByRef": null,
      "createTime": "2026-01-08T04:33:04.000+00:00",
      "lastModifiedByRef": null,
      "lastUpdatedTime": "2026-01-08T04:33:04.000+00:00",
      "lastChangedInQB": null,
      "synchronized": null
    },
    "customField": [],
    "attachableRef": [],
    "domain": "QBO",
    "status": null,
    "sparse": false,
    "name": "Rent or Lease",
    "subAccount": false,
    "parentRef": null,
    "description": null,
    "fullyQualifiedName": "Rent or Lease",
    "accountAlias": null,
    "txnLocationType": null,
    "active": true,
    "classification": "EXPENSE",
    "accountType": "EXPENSE",
    "accountSubType": null,
    "accountPurposes": [],
    "acctNum": null,
    "acctNumExtn": null,
    "bankNum": null,
    "openingBalance": null,
    "openingBalanceDate": null,
    "currentBalance": 900.0,
    "currentBalanceWithSubAccounts": 900.0,
    "currencyRef": {
      "value": "USD",
      "name": "United States Dollar",
      "type": null
    },
    "taxAccount": null,
    "taxCodeRef": null,
    "onlineBankingEnabled": null,
    "journalCodeRef": null,
    "accountEx": null,
    "finame": null
  },
  {
    "id": "29",
    "syncToken": "0",
    "metaData": {
      "createdByRef": null,
      "createTime": "2026-01-08T04:33:04.000+00:00",
      "lastModifiedByRef": null,
      "lastUpdatedTime": "2026-01-08T04:33:04.000+00:00",
      "lastChangedInQB": null,
      "synchronized": null
    },
    "customField": [],
    "attachableRef": [],
    "domain": "QBO",
    "status": null,
    "sparse": false,
    "name": "Equipment Rental",
    "subAccount": false,
    "parentRef": null,
    "description": null,
    "fullyQualifiedName": "Equipment Rental",
    "accountAlias": null,
    "txnLocationType": null,
    "active": true,
    "classification": "ASSET",
    "accountType": "FIXED_ASSET",
    "accountSubType": null,
    "accountPurposes": [],
    "acctNum": null,
    "acctNumExtn": null,
    "bankNum": null,
    "openingBalance": null,
    "openingBalanceDate": null,
    "currentBalance": 112.0,
    "currentBalanceWithSubAccounts": 112.0,
    "currencyRef": {
      "value": "USD",
      "name": "United States Dollar",
      "type": null
    },
    "taxAccount": null,
    "taxCodeRef": null,
    "onlineBankingEnabled": null,
    "journalCodeRef": null,
    "accountEx": null,
    "finame": null
  },
  {
    "id": "33",
    "syncToken": "0",
    "metaData": {
      "createdByRef": null,
      "createTime": "2026-01-08T04:33:04.000+00:00",
      "lastModifiedByRef": null,
      "lastUpdatedTime": "2026-01-08T04:33:04.000+00:00",
      "lastChangedInQB": null,
      "synchronized": null
    },
    "customField": [],
    "attachableRef": [],
    "domain": "QBO",
    "status": null,
    "sparse": false,
    "name": "Accounts Payable (A/P)",
    "subAccount": false,
    "parentRef": null,
    "description": null,
    "fullyQualifiedName": "Accounts Payable (A/P)",
    "accountAlias": null,
    "txnLocationType": null,
    "active": true,
    "classification": "LIABILITY",
    "accountType": "ACCOUNTS_PAYABLE",
    "accountSubType": null,
    "accountPurposes": [],
    "acctNum": null,
    "acctNumExtn": null,
    "bankNum": null,
    "openingBalance": null,
    "openingBalanceDate": null,
    "currentBalance": 1602.67,
    "currentBalanceWithSubAccounts": 1602.67,
    "currencyRef": {
      "value": "USD",
      "name": "United States Dollar",
      "type": null
    },
    "taxAccount": null,
    "taxCodeRef": null,
    "onlineBankingEnabled": null,
    "journalCodeRef": null,
    "accountEx": null,
    "finame": null
  },
  {
    "id": "34",
    "syncToken": "0",
    "metaData": {
      "createdByRef": null,
      "createTime": "2026-01-08T04:33:04.000+00:00",
      "lastModifiedByRef": null,
      "lastUpdatedTime": "2026-01-08T04:33:04.000+00:00",
      "lastChangedInQB": null,
      "synchronized": null
    },
    "customField": [],
    "attachableRef": [],
    "domain": "QBO",
    "status": null,
    "sparse": false,
    "name": "Opening Balance Equity",
    "subAccount": false,
    "parentRef": null,
    "description": null,
    "fullyQualifiedName": "Opening Balance Equity",
    "accountAlias": null,
    "txnLocationType": null,
    "active": true,
    "classification": "EQUITY",
    "accountType": "EQUITY",
    "accountSubType": null,
    "accountPurposes": [],
    "acctNum": null,
    "acctNumExtn": null,
    "bankNum": null,
    "openingBalance": null,
    "openingBalanceDate": null,
    "currentBalance": -9337.5,
    "currentBalanceWithSubAccounts": -9337.5,
    "currencyRef": {
      "value": "USD",
      "name": "United States Dollar",
      "type": null
    },
    "taxAccount": null,
    "taxCodeRef": null,
    "onlineBankingEnabled": null,
    "journalCodeRef": null,
    "accountEx": null,
    "finame": null
  },
  {
    "id": "35",
    "syncToken": "0",
    "metaData": {
      "createdByRef": null,
      "createTime": "2026-01-08T04:33:04.000+00:00",
      "lastModifiedByRef": null,
      "lastUpdatedTime": "2026-01-08T04:33:04.000+00:00",
      "lastChangedInQB": null,
      "synchronized": null
    },
    "customField": [],
    "attachableRef": [],
    "domain": "QBO",
    "status": null,
    "sparse": false,
    "name": "Checking",
    "subAccount": false,
    "parentRef": null,
    "description": null,
    "fullyQualifiedName": "Checking",
    "accountAlias": null,
    "txnLocationType": null,
    "active": true,
    "classification": "ASSET",
    "accountType": "BANK",
    "accountSubType": null,
    "accountPurposes": [],
    "acctNum": null,
    "acctNumExtn": null,
    "bankNum": null,
    "openingBalance": null,
    "openingBalanceDate": null,
    "currentBalance": 1201.0,
    "currentBalanceWithSubAccounts": 1201.0,
    "currencyRef": {
      "value": "USD",
      "name": "United States Dollar",
      "type": null
    },
    "taxAccount": null,
    "taxCodeRef": null,
    "onlineBankingEnabled": null,
    "journalCodeRef": null,
    "accountEx": null,
    "finame": null
  },
  {
    "id": "36",
    "syncToken": "0",
    "metaData": {
      "createdByRef": null,
      "createTime": "2026-01-08T04:33:04.000+00:00",
      "lastModifiedByRef": null,
      "lastUpdatedTime": "2026-01-08T04:33:04.000+00:00",
      "lastChangedInQB": null,
      "synchronized": null
    },
    "customField": [],
    "attachableRef": [],
    "domain": "QBO",
    "status": null,
    "sparse": false,
    "name": "Savings",
    "subAccount": false,
    "parentRef": null,
    "description": null,
    "fullyQualifiedName": "Savings",
    "accountAlias": null,
    "txnLocationType": null,
    "active": true,
    "classification": "ASSET",
    "accountType": "BANK",
    "accountSubType": null,
    "accountPurposes": [],
    "acctNum": null,
    "acctNumExtn": null,
    "bankNum": null,
    "openingBalance": null,
    "openingBalanceDate": null,
    "currentBalance": 800.0,
    "currentBalanceWithSubAccounts": 800.0,
    "currencyRef": {
      "value": "USD",
      "name": "United States Dollar",
      "type": null
    },
    "taxAccount": null,
    "taxCodeRef": null,
    "onlineBankingEnabled": null,
    "journalCodeRef": null,
    "accountEx": null,
    "finame": null
  },
  {
    "id": "41",
    "syncToken": "0",
    "metaData": {
      "createdByRef": null,
      "createTime": "2026-01-08T04:33:04.000+00:00",
      "lastModifiedByRef": null,
      "lastUpdatedTime": "2026-01-08T04:33:04.000+00:00",
      "lastChangedInQB": null,
      "synchronized": null
    },
    "customField": [],
    "attachableRef": [],
    "domain": "QBO",
    "status": null,
    "sparse": false,
    "name": "Mastercard",
    "subAccount": false,
    "parentRef": null,
    "description": null,
    "fullyQualifiedName": "Mastercard",
    "accountAlias": null,
    "txnLocationType": null,
    "active": true,
    "classification": "LIABILITY",
    "accountType": "CREDIT_CARD",
    "accountSubType": null,
    "accountPurposes": [],
    "acctNum": null,
    "acctNumExtn": null,
    "bankNum": null,
    "openingBalance": null,
    "openingBalanceDate": null,
    "currentBalance": 157.72,
    "currentBalanceWithSubAccounts": 157.72,
    "currencyRef": {
      "value": "USD",
      "name": "United States Dollar",
      "type": null
    },
    "taxAccount": null,
    "taxCodeRef": null,
    "onlineBankingEnabled": null,
    "journalCodeRef": null,
    "accountEx": null,
    "finame": null
  },
  {
    "id": "43",
    "syncToken": "0",
    "metaData": {
      "createdByRef": null,
      "createTime": "2026-01-08T04:33:04.000+00:00",
      "lastModifiedByRef": null,
      "lastUpdatedTime": "2026-01-08T04:33:04.000+00:00",
      "lastChangedInQB": null,
      "synchronized": null
    },
    "customField": [],
    "attachableRef": [],
    "domain": "QBO",
    "status": null,
    "sparse": false,
    "name": "Loan Payable",
    "subAccount": false,
    "parentRef": null,
    "description": null,
    "fullyQualifiedName": "Loan Payable",
    "accountAlias": null,
    "txnLocationType": null,
    "active": true,
    "classification": "LIABILITY",
    "accountType": "ACCOUNTS_PAYABLE",
    "accountSubType": null,
    "accountPurposes": [],
    "acctNum": null,
    "acctNumExtn": null,
    "bankNum": null,
    "openingBalance": null,
    "openingBalanceDate": null,
    "currentBalance": 4000.0,
    "currentBalanceWithSubAccounts": 4000.0,
    "currencyRef": {
      "value": "USD",
      "name": "United States Dollar",
      "type": null
    },
    "taxAccount": null,
    "taxCodeRef": null,
    "onlineBankingEnabled": null,
    "journalCodeRef": null,
    "accountEx": null,
    "finame": null
  },
  {
    "id": "44",
    "syncToken": "0",
    "metaData": {
      "createdByRef": null,
      "createTime": "2026-01-08T04:33:04.000+00:00",
      "lastModifiedByRef": null,
      "lastUpdatedTime": "2026-01-08T04:33:04.000+00:00",
      "lastChangedInQB": null,
      "synchronized": null
    },
    "customField": [],
    "attachableRef": [],
    "domain": "QBO",
    "status": null,
    "sparse": false,
    "name": "Notes Payable",
    "subAccount": false,
    "parentRef": null,
    "description": null,
    "fullyQualifiedName": "Notes Payable",
    "accountAlias": null,
    "txnLocationType": null,
    "active": true,
    "classification": "LIABILITY",
    "accountType": "ACCOUNTS_PAYABLE",
    "accountSubType": null,
    "accountPurposes": [],
    "acctNum": null,
    "acctNumExtn": null,
    "bankNum": null,
    "openingBalance": null,
    "openingBalanceDate": null,
    "currentBalance": 25000.0,
    "currentBalanceWithSubAccounts": 25000.0,
    "currencyRef": {
      "value": "USD",
      "name": "United States Dollar",
      "type": null
    },
    "taxAccount": null,
    "taxCodeRef": null,
    "onlineBankingEnabled": null,
    "journalCodeRef": null,
    "accountEx": null,
    "finame": null
  },
  {
    "id": "45",
    "syncToken": "0",
    "metaData": {
      "createdByRef": null,
      "createTime": "2026-01-08T04:33:04.000+00:00",
      "lastModifiedByRef": null,
      "lastUpdatedTime": "2026-01-08T04:33:04.000+00:00",
      "lastChangedInQB": null,
      "synchronized": null
    },
    "customField": [],
    "attachableRef": [],
    "domain": "QBO",
    "status": null,
    "sparse": false,
    "name": "Landscaping Services",
    "subAccount": false,
    "parentRef": null,
    "description": null,
    "fullyQualifiedName": "Landscaping Services",
    "accountAlias": null,
    "txnLocationType": null,
    "active": true,
    "classification": "REVENUE",
    "accountType": "INCOME",
    "accountSubType": null,
    "accountPurposes": [],
    "acctNum": null,
    "acctNumExtn": null,
    "bankNum": null,
    "openingBalance": null,
    "openingBalanceDate": null,
    "currentBalance": 0.0,
    "currentBalanceWithSubAccounts": 0.0,
    "currencyRef": {
      "value": "USD",
      "name": "United States Dollar",
      "type": null
    },
    "taxAccount": null,
    "taxCodeRef": null,
    "onlineBankingEnabled": null,
    "journalCodeRef": null,
    "accountEx": null,
    "finame": null
  },
  {
    "id": "54",
    "syncToken": "0",
    "metaData": {
      "createdByRef": null,
      "createTime": "2026-01-08T04:33:04.000+00:00",
      "lastModifiedByRef": null,
      "lastUpdatedTime": "2026-01-08T04:33:04.000+00:00",
      "lastChangedInQB": null,
      "synchronized": null
    },
    "customField": [],
    "attachableRef": [],
    "domain": "QBO",
    "status": null,
    "sparse": false,
    "name": "Pest Control Services",
    "subAccount": false,
    "parentRef": null,
    "description": null,
    "fullyQualifiedName": "Pest Control Services",
    "accountAlias": null,
    "txnLocationType": null,
    "active": true,
    "classification": "REVENUE",
    "accountType": "INCOME",
    "accountSubType": null,
    "accountPurposes": [],
    "acctNum": null,
    "acctNumExtn": null,
    "bankNum": null,
    "openingBalance": null,
    "openingBalanceDate": null,
    "currentBalance": 110.0,
    "currentBalanceWithSubAccounts": 110.0,
    "currencyRef": {
      "value": "USD",
      "name": "United States Dollar",
      "type": null
    },
    "taxAccount": null,
    "taxCodeRef": null,
    "onlineBankingEnabled": null,
    "journalCodeRef": null,
    "accountEx": null,
    "finame": null
  },
  {
    "id": "55",
    "syncToken": "0",
    "metaData": {
      "createdByRef": null,
      "createTime": "2026-01-08T04:33:04.000+00:00",
      "lastModifiedByRef": null,
      "lastUpdatedTime": "2026-01-08T04:33:04.000+00:00",
      "lastChangedInQB": null,
      "synchronized": null
    },
    "customField": [],
    "attachableRef": [],
    "domain": "QBO",
    "status": null,
    "sparse": false,
    "name": "Automobile",
    "subAccount": false,
    "parentRef": null,
    "description": null,
    "fullyQualifiedName": "Automobile",
    "accountAlias": null,
    "txnLocationType": null,
    "active": true,
    "classification": "ASSET",
    "accountType": "OTHER_CURRENT_ASSET",
    "accountSubType": null,
    "accountPurposes": [],
    "acctNum": null,
    "acctNumExtn": null,
    "bankNum": null,
    "openingBalance": null,
    "openingBalanceDate": null,
    "currentBalance": 0.0,
    "currentBalanceWithSubAccounts": 0.0,
    "currencyRef": {
      "value": "USD",
      "name": "United States Dollar",
      "type": null
    },
    "taxAccount": null,
    "taxCodeRef": null,
    "onlineBankingEnabled": null,
    "journalCodeRef": null,
    "accountEx": null,
    "finame": null
  },
  {
    "id": "58",
    "syncToken": "0",
    "metaData": {
      "createdByRef": null,
      "createTime": "2026-01-08T04:33:04.000+00:00",
      "lastModifiedByRef": null,
      "lastUpdatedTime": "2026-01-08T04:33:04.000+00:00",
      "lastChangedInQB": null,
      "synchronized": null
    },
    "customField": [],
    "attachableRef": [],
    "domain": "QBO",
    "status": null,
    "sparse": false,
    "name": "Job Expenses",
    "subAccount": false,
    "parentRef": null,
    "description": null,
    "fullyQualifiedName": "Job Expenses",
    "accountAlias": null,
    "txnLocationType": null,
    "active": true,
    "classification": "ASSET",
    "accountType": "OTHER_CURRENT_ASSET",
    "accountSubType": null,
    "accountPurposes": [],
    "acctNum": null,
    "acctNumExtn": null,
    "bankNum": null,
    "openingBalance": null,
    "openingBalanceDate": null,
    "currentBalance": 0.0,
    "currentBalanceWithSubAccounts": 0.0,
    "currencyRef": {
      "value": "USD",
      "name": "United States Dollar",
      "type": null
    },
    "taxAccount": null,
    "taxCodeRef": null,
    "onlineBankingEnabled": null,
    "journalCodeRef": null,
    "accountEx": null,
    "finame": null
  },
  {
    "id": "72",
    "syncToken": "0",
    "metaData": {
      "createdByRef": null,
      "createTime": "2026-01-08T04:33:04.000+00:00",
      "lastModifiedByRef": null,
      "lastUpdatedTime": "2026-01-08T04:33:04.000+00:00",
      "lastChangedInQB": null,
      "synchronized": null
    },
    "customField": [],
    "attachableRef": [],
    "domain": "QBO",
    "status": null,
    "sparse": false,
    "name": "Maintenance and Repair",
    "subAccount": false,
    "parentRef": null,
    "description": null,
    "fullyQualifiedName": "Maintenance and Repair",
    "accountAlias": null,
    "txnLocationType": null,
    "active": true,
    "classification": "EXPENSE",
    "accountType": "EXPENSE",
    "accountSubType": null,
    "accountPurposes": [],
    "acctNum": null,
    "acctNumExtn": null,
    "bankNum": null,
    "openingBalance": null,
    "openingBalanceDate": null,
    "currentBalance": 0.0,
    "currentBalanceWithSubAccounts": 0.0,
    "currencyRef": {
      "value": "USD",
      "name": "United States Dollar",
      "type": null
    },
    "taxAccount": null,
    "taxCodeRef": null,
    "onlineBankingEnabled": null,
    "journalCodeRef": null,
    "accountEx": null,
    "finame": null
  },
  {
    "id": "79",
    "syncToken": "0",
    "metaData": {
      "createdByRef": null,
      "createTime": "2026-01-08T04:33:04.000+00:00",
      "lastModifiedByRef": null,
      "lastUpdatedTime": "2026-01-08T04:33:04.000+00:00",
      "lastChangedInQB": null,
      "synchronized": null
    },
    "customField": [],
    "attachableRef": [],
    "domain": "QBO",
    "status": null,
    "sparse": false,
    "name": "Sales of Product Income",
    "subAccount": false,
    "parentRef": null,
    "description": null,
    "fullyQualifiedName": "Sales of Product Income",
    "accountAlias": null,
    "txnLocationType": null,
    "active": true,
    "classification": "REVENUE",
    "accountType": "INCOME",
    "accountSubType": null,
    "accountPurposes": [],
    "acctNum": null,
    "acctNumExtn": null,
    "bankNum": null,
    "openingBalance": null,
    "openingBalanceDate": null,
    "currentBalance": 912.75,
    "currentBalanceWithSubAccounts": 912.75,
    "currencyRef": {
      "value": "USD",
      "name": "United States Dollar",
      "type": null
    },
    "taxAccount": null,
    "taxCodeRef": null,
    "onlineBankingEnabled": null,
    "journalCodeRef": null,
    "accountEx": null,
    "finame": null
  },
  {
    "id": "80",
    "syncToken": "0",
    "metaData": {
      "createdByRef": null,
      "createTime": "2026-01-08T04:33:04.000+00:00",
      "lastModifiedByRef": null,
      "lastUpdatedTime": "2026-01-08T04:33:04.000+00:00",
      "lastChangedInQB": null,
      "synchronized": null
    },
    "customField": [],
    "attachableRef": [],
    "domain": "QBO",
    "status": null,
    "sparse": false,
    "name": "Cost of Goods Sold",
    "subAccount": false,
    "parentRef": null,
    "description": null,
    "fullyQualifiedName": "Cost of Goods Sold",
    "accountAlias": null,
    "txnLocationType": null,
    "active": true,
    "classification": "EXPENSE",
    "accountType": "COST_OF_GOODS_SOLD",
    "accountSubType": null,
    "accountPurposes": [],
    "acctNum": null,
    "acctNumExtn": null,
    "bankNum": null,
    "openingBalance": null,
    "openingBalanceDate": null,
    "currentBalance": 405.0,
    "currentBalanceWithSubAccounts": 405.0,
    "currencyRef": {
      "value": "USD",
      "name": "United States Dollar",
      "type": null
    },
    "taxAccount": null,
    "taxCodeRef": null,
    "onlineBankingEnabled": null,
    "journalCodeRef": null,
    "accountEx": null,
    "finame": null
  },
  {
    "id": "81",
    "syncToken": "0",
    "metaData": {
      "createdByRef": null,
      "createTime": "2026-01-08T04:33:04.000+00:00",
      "lastModifiedByRef": null,
      "lastUpdatedTime": "2026-01-08T04:33:04.000+00:00",
      "lastChangedInQB": null,
      "synchronized": null
    },
    "customField": [],
    "attachableRef": [],
    "domain": "QBO",
    "status": null,
    "sparse": false,
    "name": "Inventory Asset",
    "subAccount": false,
    "parentRef": null,
    "description": null,
    "fullyQualifiedName": "Inventory Asset",
    "accountAlias": null,
    "txnLocationType": null,
    "active": true,
    "classification": "ASSET",
    "accountType": "OTHER_CURRENT_ASSET",
    "accountSubType": null,
    "accountPurposes": [],
    "acctNum": null,
    "acctNumExtn": null,
    "bankNum": null,
    "openingBalance": null,
    "openingBalanceDate": null,
    "currentBalance": 596.25,
    "currentBalanceWithSubAccounts": 596.25,
    "currencyRef": {
      "value": "USD",
      "name": "United States Dollar",
      "type": null
    },
    "taxAccount": null,
    "taxCodeRef": null,
    "onlineBankingEnabled": null,
    "journalCodeRef": null,
    "accountEx": null,
    "finame": null
  },
  {
    "id": "82",
    "syncToken": "0",
    "metaData": {
      "createdByRef": null,
      "createTime": "2026-01-08T04:33:04.000+00:00",
      "lastModifiedByRef": null,
      "lastUpdatedTime": "2026-01-08T04:33:04.000+00:00",
      "lastChangedInQB": null,
      "synchronized": null
    },
    "customField": [],
    "attachableRef": [],
    "domain": "QBO",
    "status": null,
    "sparse": false,
    "name": "Design income",
    "subAccount": false,
    "parentRef": null,
    "description": null,
    "fullyQualifiedName": "Design income",
    "accountAlias": null,
    "txnLocationType": null,
    "active": true,
    "classification": "REVENUE",
    "accountType": "INCOME",
    "accountSubType": null,
    "accountPurposes": [],
    "acctNum": null,
    "acctNumExtn": null,
    "bankNum": null,
    "openingBalance": null,
    "openingBalanceDate": null,
    "currentBalance": 2250.0,
    "currentBalanceWithSubAccounts": 2250.0,
    "currencyRef": {
      "value": "USD",
      "name": "United States Dollar",
      "type": null
    },
    "taxAccount": null,
    "taxCodeRef": null,
    "onlineBankingEnabled": null,
    "journalCodeRef": null,
    "accountEx": null,
    "finame": null
  },
  {
    "id": "84",
    "syncToken": "0",
    "metaData": {
      "createdByRef": null,
      "createTime": "2026-01-08T04:33:04.000+00:00",
      "lastModifiedByRef": null,
      "lastUpdatedTime": "2026-01-08T04:33:04.000+00:00",
      "lastChangedInQB": null,
      "synchronized": null
    },
    "customField": [],
    "attachableRef": [],
    "domain": "QBO",
    "status": null,
    "sparse": false,
    "name": "Accounts Receivable (A/R)",
    "subAccount": false,
    "parentRef": null,
    "description": null,
    "fullyQualifiedName": "Accounts Receivable (A/R)",
    "accountAlias": null,
    "txnLocationType": null,
    "active": true,
    "classification": "ASSET",
    "accountType": "ACCOUNTS_RECEIVABLE",
    "accountSubType": null,
    "accountPurposes": [],
    "acctNum": null,
    "acctNumExtn": null,
    "bankNum": null,
    "openingBalance": null,
    "openingBalanceDate": null,
    "currentBalance": 5281.52,
    "currentBalanceWithSubAccounts": 5281.52,
    "currencyRef": {
      "value": "USD",
      "name": "United States Dollar",
      "type": null
    },
    "taxAccount": null,
    "taxCodeRef": null,
    "onlineBankingEnabled": null,
    "journalCodeRef": null,
    "accountEx": null,
    "finame": null
  },
  {
    "id": "86",
    "syncToken": "0",
    "metaData": {
      "createdByRef": null,
      "createTime": "2026-01-08T04:33:04.000+00:00",
      "lastModifiedByRef": null,
      "lastUpdatedTime": "2026-01-08T04:33:04.000+00:00",
      "lastChangedInQB": null,
      "synchronized": null
    },
    "customField": [],
    "attachableRef": [],
    "domain": "QBO",
    "status": null,
    "sparse": false,
    "name": "Discounts given",
    "subAccount": false,
    "parentRef": null,
    "description": null,
    "fullyQualifiedName": "Discounts given",
    "accountAlias": null,
    "txnLocationType": null,
    "active": true,
    "classification": "LIABILITY",
    "accountType": "OTHER_CURRENT_LIABILITY",
    "accountSubType": null,
    "accountPurposes": [],
    "acctNum": null,
    "acctNumExtn": null,
    "bankNum": null,
    "openingBalance": null,
    "openingBalanceDate": null,
    "currentBalance": -89.5,
    "currentBalanceWithSubAccounts": -89.5,
    "currencyRef": {
      "value": "USD",
      "name": "United States Dollar",
      "type": null
    },
    "taxAccount": null,
    "taxCodeRef": null,
    "onlineBankingEnabled": null,
    "journalCodeRef": null,
    "accountEx": null,
    "finame": null
  },
  {
    "id": "89",
    "syncToken": "0",
    "metaData": {
      "createdByRef": null,
      "createTime": "2026-01-08T04:33:04.000+00:00",
      "lastModifiedByRef": null,
      "lastUpdatedTime": "2026-01-08T04:33:04.000+00:00",
      "lastChangedInQB": null,
      "synchronized": null
    },
    "customField": [],
    "attachableRef": [],
    "domain": "QBO",
    "status": null,
    "sparse": false,
    "name": "Arizona Dept. of Revenue Payable",
    "subAccount": false,
    "parentRef": null,
    "description": null,
    "fullyQualifiedName": "Arizona Dept. of Revenue Payable",
    "accountAlias": null,
    "txnLocationType": null,
    "active": true,
    "classification": "LIABILITY",
    "accountType": "ACCOUNTS_PAYABLE",
    "accountSubType": null,
    "accountPurposes": [],
    "acctNum": null,
    "acctNumExtn": null,
    "bankNum": null,
    "openingBalance": null,
    "openingBalanceDate": null,
    "currentBalance": 0.0,
    "currentBalanceWithSubAccounts": 0.0,
    "currencyRef": {
      "value": "USD",
      "name": "United States Dollar",
      "type": null
    },
    "taxAccount": null,
    "taxCodeRef": null,
    "onlineBankingEnabled": null,
    "journalCodeRef": null,
    "accountEx": null,
    "finame": null
  },
  {
    "id": "90",
    "syncToken": "0",
    "metaData": {
      "createdByRef": null,
      "createTime": "2026-01-08T04:33:04.000+00:00",
      "lastModifiedByRef": null,
      "lastUpdatedTime": "2026-01-08T04:33:04.000+00:00",
      "lastChangedInQB": null,
      "synchronized": null
    },
    "customField": [],
    "attachableRef": [],
    "domain": "QBO",
    "status": null,
    "sparse": false,
    "name": "Board of Equalization Payable",
    "subAccount": false,
    "parentRef": null,
    "description": null,
    "fullyQualifiedName": "Board of Equalization Payable",
    "accountAlias": null,
    "txnLocationType": null,
    "active": true,
    "classification": "LIABILITY",
    "accountType": "ACCOUNTS_PAYABLE",
    "accountSubType": null,
    "accountPurposes": [],
    "acctNum": null,
    "acctNumExtn": null,
    "bankNum": null,
    "openingBalance": null,
    "openingBalanceDate": null,
    "currentBalance": 370.94,
    "currentBalanceWithSubAccounts": 370.94,
    "currencyRef": {
      "value": "USD",
      "name": "United States Dollar",
      "type": null
    },
    "taxAccount": null,
    "taxCodeRef": null,
    "onlineBankingEnabled": null,
    "journalCodeRef": null,
    "accountEx": null,
    "finame": null
  }
]